{"Id":2020212,"LifeProId":202,"ParentId":0,"Type":1,"Name":"Rubber","Quality":0,"FurnitureId":0,"Sort":215,"Des":"A resilient essence distilled from natural resins, the wellspring of elasticity and protection.","NeedLevel":4,"IsConditonUnlock":true,"UnlockType":1,"UnlockCondition":["Alchemy Lv.4 to unlock"],"Cost":{"Id":20003,"Name":"Focus","Type":4,"Icon":"item_icons_energy","Quality":3,"amount":0},"Time":5,"NeedMaterialType":1,"NeedMaterial":[[1092048,4]],"RandomWeight":0,"Award":[21510014],"SpecialAward":[],"ExtraAward":[],"MasteryAward":[],"BindOrNot":1,"Exp":{"Id":31051,"Name":"Alchemy EXP","Type":31,"Icon":"item_icons_alchemy_exp_01","Quality":1,"amount":2},"QuickJumpType":1,"QuickJump":[8,5,503663],"Icon":"item_icons_lifematerial_rubber01","RelatedItemId":1083025,"Hide":false,"awardGroups":[[{"itemId":1083025,"Name":"Rubber","rate":1,"minAmount":1,"maxAmount":1,"Icon":"item_icons_lifematerial_rubber01","Quality":0}]],"talent_lv0_yields":[[{"itemId":1083025,"Name":"Rubber","rate":1,"Icon":"item_icons_lifematerial_rubber01","Quality":0,"amount":1}]],"talent_lv1_yields":[[{"itemId":1083025,"Name":"Rubber","rate":1,"Icon":"item_icons_lifematerial_rubber01","Quality":0,"amount":1}]],"talent_lv2_yields":[[{"itemId":1083025,"Name":"Rubber","rate":1,"Icon":"item_icons_lifematerial_rubber01","Quality":0,"amount":1}]],"talent_lv3_yields":[[{"itemId":1083025,"Name":"Rubber","rate":1,"Icon":"item_icons_lifematerial_rubber01","Quality":0,"amount":1}]],"materials":[{"Id":1092048,"Name":"Resin","Type":109,"Icon":"item_icons_lifematerial_resin01","Quality":1,"amount":4}],"recipeVariants":[{"Id":2020212,"LifeProId":202,"ParentId":0,"Type":1,"Name":"Rubber","Quality":0,"FurnitureId":0,"Sort":215,"Des":"A resilient essence distilled from natural resins, the wellspring of elasticity and protection.","NeedLevel":4,"IsConditonUnlock":true,"UnlockType":1,"UnlockCondition":["Alchemy Lv.4 to unlock"],"Cost":{"Id":20003,"Name":"Focus","Type":4,"Icon":"item_icons_energy","Quality":3,"amount":0},"Time":5,"NeedMaterialType":1,"NeedMaterial":[[1092048,4]],"RandomWeight":0,"Award":[21510014],"SpecialAward":[],"ExtraAward":[],"MasteryAward":[],"BindOrNot":1,"Exp":{"Id":31051,"Name":"Alchemy EXP","Type":31,"Icon":"item_icons_alchemy_exp_01","Quality":1,"amount":2},"QuickJumpType":1,"QuickJump":[8,5,503663],"Icon":"item_icons_lifematerial_rubber01","RelatedItemId":1083025,"Hide":false,"awardGroups":[[{"itemId":1083025,"Name":"Rubber","rate":1,"minAmount":1,"maxAmount":1,"Icon":"item_icons_lifematerial_rubber01","Quality":0}]],"talent_lv0_yields":[[{"itemId":1083025,"Name":"Rubber","rate":1,"Icon":"item_icons_lifematerial_rubber01","Quality":0,"amount":1}]],"talent_lv1_yields":[[{"itemId":1083025,"Name":"Rubber","rate":1,"Icon":"item_icons_lifematerial_rubber01","Quality":0,"amount":1}]],"talent_lv2_yields":[[{"itemId":1083025,"Name":"Rubber","rate":1,"Icon":"item_icons_lifematerial_rubber01","Quality":0,"amount":1}]],"talent_lv3_yields":[[{"itemId":1083025,"Name":"Rubber","rate":1,"Icon":"item_icons_lifematerial_rubber01","Quality":0,"amount":1}]],"materials":[{"Id":1092048,"Name":"Resin","Icon":"item_icons_lifematerial_resin01","Icon2":"","Type":109,"GroupId":0,"Quality":1,"SortID":109,"Description":"Collected resource that can be processed further with Life Skills.","Description2":"Versatile in application, it is primarily used to harden and bond leather with lasting strength.","SexLimit":0,"Overlap":9999,"TimeType":0,"TimeLimit":"","DropModel":0,"CorrelationId":0,"SpecialDisplayType":0,"SpecialTips":0,"QuickUse":0,"IsNotice":false,"GetTips":0,"Warehouse":[101,1],"Discard":1,"LuckyTag":0,"sellable":false,"sellData":null,"sources":[{"Name":"Botany Exchange","Icon":"ui/atlas/item/c_tab_icon/com_icon_tab_83","Level":0,"RoleLevel":0},{"Name":"Botany","Icon":"ui/atlas/item/c_tab_icon/com_icon_tab_306","Level":0,"RoleLevel":0},{"Name":"Botany","Icon":"ui/atlas/life_profession/life_icon_collect","Level":0,"RoleLevel":17,"lifeSkillSource":{"Id":20000021,"LifeProId":101,"Name":"Thin Twig","Sort":14,"Quality":0,"Des":"Above the Cliff Ruins lies a forest, its scattered clearings nestled beneath the sheltering canopy of trees.","Icon":"item_icons_lifematerial_branch01","NeedLevel":[0,1],"UnlockCondition":[],"UnlockConditionZeroCost":["Botany Lv.1 to unlock"],"Cost":{"Id":20003,"Name":"Focus","Type":4,"Icon":"item_icons_energy","Quality":3,"amount":0},"FreeAward":21000640,"Award":0,"ExtraAward":[],"QuickJumpType":1,"QuickJump":[7,7,20000021],"Scene":7,"ProduceArea":"Asteria Plains","Hide":false,"awardGroups":[[{"itemId":31001,"Name":"Botany EXP","rate":0.1,"minAmount":15,"maxAmount":25,"Icon":"item_icons_collect_exp_01","Quality":1,"isFree":true},{"itemId":1092050,"Name":"Twig","rate":1,"minAmount":3,"maxAmount":6,"Icon":"item_icons_lifematerial_branch01","Quality":0,"isFree":true},{"itemId":1092048,"Name":"Resin","rate":0.8325,"minAmount":2,"maxAmount":3,"Icon":"item_icons_lifematerial_resin01","Quality":1,"isFree":true},{"itemId":1092058,"Name":"Engram Dust Crystals","rate":0.02,"minAmount":1,"maxAmount":1,"Icon":"item_icons_lifematerial_starlightdust_crystal01","Quality":3,"isFree":true}]],"materials":[]}},{"Name":"Botany","Icon":"ui/atlas/life_profession/life_icon_collect","Level":0,"RoleLevel":17,"lifeSkillSource":{"Id":20000022,"LifeProId":101,"Name":"Wood Branch","Sort":15,"Quality":1,"Des":"Isles of Pale Azure Lake, adrift beneath a cathedral of trees.","Icon":"item_icons_lifematerial_branch02","NeedLevel":[0,10],"UnlockCondition":[],"UnlockConditionZeroCost":["Botany Lv.10 to unlock"],"Cost":{"Id":20003,"Name":"Focus","Type":4,"Icon":"item_icons_energy","Quality":3,"amount":0},"FreeAward":21000650,"Award":0,"ExtraAward":[],"QuickJumpType":1,"QuickJump":[7,7,20000022],"Scene":7,"ProduceArea":"Asteria Plains","Hide":false,"awardGroups":[[{"itemId":31001,"Name":"Botany EXP","rate":0.1,"minAmount":15,"maxAmount":25,"Icon":"item_icons_collect_exp_01","Quality":1,"isFree":true},{"itemId":1092050,"Name":"Twig","rate":0.5,"minAmount":3,"maxAmount":6,"Icon":"item_icons_lifematerial_branch01","Quality":0,"isFree":true},{"itemId":1092050,"Name":"Twig","rate":0.5,"minAmount":2,"maxAmount":5,"Icon":"item_icons_lifematerial_branch01","Quality":0,"isFree":true},{"itemId":1092048,"Name":"Resin","rate":0.8325,"minAmount":3,"maxAmount":5,"Icon":"item_icons_lifematerial_resin01","Quality":1,"isFree":true},{"itemId":1092049,"Name":"Tree Resin","rate":0.369,"minAmount":1,"maxAmount":1,"Icon":"item_icons_lifematerial_tree_wax01","Quality":2,"isFree":true},{"itemId":1092035,"Name":"Silkworm Cocoons","rate":0.041,"minAmount":1,"maxAmount":1,"Icon":"item_icons_lifematerial_cocoon01","Quality":2,"isFree":true},{"itemId":1092058,"Name":"Engram Dust Crystals","rate":0.03,"minAmount":1,"maxAmount":1,"Icon":"item_icons_lifematerial_starlightdust_crystal01","Quality":3,"isFree":true}]],"materials":[]}},{"Name":"Botany","Icon":"ui/atlas/life_profession/life_icon_collect","Level":0,"RoleLevel":17,"lifeSkillSource":{"Id":20000023,"LifeProId":101,"Name":"Branch Cluster","Sort":16,"Quality":2,"Des":"Littoral shallows adrift in dappled sylvan shadows.","Icon":"item_icons_lifematerial_stalk03","NeedLevel":[0,17],"UnlockCondition":[],"UnlockConditionZeroCost":["Botany Lv.17 to unlock"],"Cost":{"Id":20003,"Name":"Focus","Type":4,"Icon":"item_icons_energy","Quality":3,"amount":0},"FreeAward":21000660,"Award":0,"ExtraAward":[],"QuickJumpType":1,"QuickJump":[71,7,20000023],"Scene":71,"ProduceArea":"Duskdye Woods","Hide":false,"awardGroups":[[{"itemId":31001,"Name":"Botany EXP","rate":0.1,"minAmount":15,"maxAmount":25,"Icon":"item_icons_collect_exp_01","Quality":1,"isFree":true},{"itemId":1092050,"Name":"Twig","rate":0.4,"minAmount":3,"maxAmount":6,"Icon":"item_icons_lifematerial_branch01","Quality":0,"isFree":true},{"itemId":1092050,"Name":"Twig","rate":0.6,"minAmount":3,"maxAmount":6,"Icon":"item_icons_lifematerial_branch01","Quality":0,"isFree":true},{"itemId":1092048,"Name":"Resin","rate":0.8325,"minAmount":4,"maxAmount":6,"Icon":"item_icons_lifematerial_resin01","Quality":1,"isFree":true},{"itemId":1092049,"Name":"Tree Resin","rate":0.41625,"minAmount":1,"maxAmount":1,"Icon":"item_icons_lifematerial_tree_wax01","Quality":2,"isFree":true},{"itemId":1092035,"Name":"Silkworm Cocoons","rate":0.41625,"minAmount":1,"maxAmount":1,"Icon":"item_icons_lifematerial_cocoon01","Quality":2,"isFree":true},{"itemId":1092058,"Name":"Engram Dust Crystals","rate":0.05,"minAmount":1,"maxAmount":1,"Icon":"item_icons_lifematerial_starlightdust_crystal01","Quality":3,"isFree":true}]],"materials":[]}}]}]}]}