{"Id":2010039,"LifeProId":201,"ParentId":0,"Type":2,"Name":"Fragrant Fresh Fruit Tea","Quality":1,"FurnitureId":0,"Sort":39,"Des":"Crafting results in either products Lv.1 or Lv.2 with a <style=\"accent-gn\">50%</style> chance. <br>A refreshingly sweet-and-tart fruit drink that lifts your spirits with every sip—as if catching the scent of joy on the breeze.","NeedLevel":1,"IsConditonUnlock":true,"UnlockType":1,"UnlockCondition":["Learn Specialization Fruit Cuisine Novice"],"Cost":{"Id":20003,"Name":"Stamina","Type":4,"Icon":"item_icons_energy","Quality":3,"amount":25},"Time":5,"NeedMaterialType":1,"NeedMaterial":[[1092001,2],[0,0],[1092130,1],[0,0]],"RandomWeight":0,"Award":[21400063],"SpecialAward":[{"Name":"Lucky Cooking Lv.1","Des":"10% chance to gain 1 extra item when cooking or processing (Does not apply to Mega Cheer-Up Treat).","UnlockCondition":[],"Icon":"ui/atlas/life_formula/life_cook/lucky_cooking_01","NeedPoint":2,"awards":[{"itemId":1010071,"Name":"Yoyo Fruit Tea Lv.1","rate":0.05,"minAmount":1,"maxAmount":1,"Icon":"item_icons_cuisine20_01","Quality":1},{"itemId":1010072,"Name":"Yoyo Fruit Tea Lv.2","rate":0.05,"minAmount":1,"maxAmount":1,"Icon":"item_icons_cuisine20_02","Quality":2}]},{"Name":"Lucky Cooking Lv.2","Des":"20% chance to gain 1 extra item when cooking or processing (Does not apply to Mega Cheer-Up Treat).","UnlockCondition":["Learn Specialization Lucky Cooking Lv.1","Server open for 6 day(s)"],"Icon":"ui/atlas/life_formula/life_cook/lucky_cooking_02","NeedPoint":2,"awards":[{"itemId":1010071,"Name":"Yoyo Fruit Tea Lv.1","rate":0.1,"minAmount":1,"maxAmount":1,"Icon":"item_icons_cuisine20_01","Quality":1},{"itemId":1010072,"Name":"Yoyo Fruit Tea Lv.2","rate":0.1,"minAmount":1,"maxAmount":1,"Icon":"item_icons_cuisine20_02","Quality":2}]},{"Name":"Lucky Cooking Lv.3","Des":"30% chance to gain 1 extra item when cooking or processing (Does not apply to Mega Cheer-Up Treat).","UnlockCondition":["Learn Specialization Lucky Cooking Lv.2","Server open for 25 day(s)"],"Icon":"ui/atlas/life_formula/life_cook/lucky_cooking_03","NeedPoint":2,"awards":[{"itemId":1010071,"Name":"Yoyo Fruit Tea Lv.1","rate":0.15,"minAmount":1,"maxAmount":1,"Icon":"item_icons_cuisine20_01","Quality":1},{"itemId":1010072,"Name":"Yoyo Fruit Tea Lv.2","rate":0.15,"minAmount":1,"maxAmount":1,"Icon":"item_icons_cuisine20_02","Quality":2}]}],"ExtraAward":[],"MasteryAward":[],"BindOrNot":0,"Exp":{"Id":31041,"Name":"Culinary​ EXP","Type":31,"Icon":"item_icons_cook_exp_01","Quality":1,"amount":100},"QuickJumpType":1,"QuickJump":[8,5,1079],"Icon":"item_icons_cuisine20_01","RelatedItemId":1010071,"Hide":false,"awardGroups":[[{"itemId":1010071,"Name":"Yoyo Fruit Tea Lv.1","rate":0.5,"minAmount":1,"maxAmount":1,"Icon":"item_icons_cuisine20_01","Quality":1},{"itemId":1010072,"Name":"Yoyo Fruit Tea Lv.2","rate":0.5,"minAmount":1,"maxAmount":1,"Icon":"item_icons_cuisine20_02","Quality":2}]],"talent_lv0_yields":[[{"itemId":1010071,"Name":"Yoyo Fruit Tea Lv.1","rate":0.5,"Icon":"item_icons_cuisine20_01","Quality":1,"amount":1}],[{"itemId":1010072,"Name":"Yoyo Fruit Tea Lv.2","rate":0.5,"Icon":"item_icons_cuisine20_02","Quality":2,"amount":1}]],"talent_lv1_yields":[[{"itemId":1010071,"Name":"Yoyo Fruit Tea Lv.1","rate":0.475,"Icon":"item_icons_cuisine20_01","Quality":1,"amount":1},{"itemId":1010071,"Name":"Yoyo Fruit Tea Lv.1","rate":0.025,"Icon":"item_icons_cuisine20_01","Quality":1,"amount":2}],[{"itemId":1010072,"Name":"Yoyo Fruit Tea Lv.2","rate":0.475,"Icon":"item_icons_cuisine20_02","Quality":2,"amount":1},{"itemId":1010072,"Name":"Yoyo Fruit Tea Lv.2","rate":0.025,"Icon":"item_icons_cuisine20_02","Quality":2,"amount":2}]],"talent_lv2_yields":[[{"itemId":1010071,"Name":"Yoyo Fruit Tea Lv.1","rate":0.45,"Icon":"item_icons_cuisine20_01","Quality":1,"amount":1},{"itemId":1010071,"Name":"Yoyo Fruit Tea Lv.1","rate":0.05,"Icon":"item_icons_cuisine20_01","Quality":1,"amount":2}],[{"itemId":1010072,"Name":"Yoyo Fruit Tea Lv.2","rate":0.45,"Icon":"item_icons_cuisine20_02","Quality":2,"amount":1},{"itemId":1010072,"Name":"Yoyo Fruit Tea Lv.2","rate":0.05,"Icon":"item_icons_cuisine20_02","Quality":2,"amount":2}]],"talent_lv3_yields":[[{"itemId":1010071,"Name":"Yoyo Fruit Tea Lv.1","rate":0.425,"Icon":"item_icons_cuisine20_01","Quality":1,"amount":1},{"itemId":1010071,"Name":"Yoyo Fruit Tea Lv.1","rate":0.075,"Icon":"item_icons_cuisine20_01","Quality":1,"amount":2}],[{"itemId":1010072,"Name":"Yoyo Fruit Tea Lv.2","rate":0.425,"Icon":"item_icons_cuisine20_02","Quality":2,"amount":1},{"itemId":1010072,"Name":"Yoyo Fruit Tea Lv.2","rate":0.075,"Icon":"item_icons_cuisine20_02","Quality":2,"amount":2}]],"materials":[{"node":"0","Id":1010071,"Name":"Yoyo Fruit Tea Lv.1","Type":101,"Icon":"item_icons_cuisine20_01","Quality":1,"recipes":[2010039]},{"parent":"0","edge":"0-1a","node":"1a","Id":1092001,"Name":"Sweet Berry","Type":109,"Icon":"item_icons_berry","Quality":0,"amount":2,"recipes":[20000010]},{"parent":"0","edge":"0-1b","node":"1b","Id":1092130,"Name":"Limpid Azure Water","Type":109,"Icon":"item_icons_water","Quality":0,"amount":1,"recipes":[20000101,20000102,20000103,20000104,20000105,20000106,20000107,20000108,20000109,20000111,20000112,20000201,20000202,20000203,20000204,20000205,20000206,20000207,20000208,20000209,20000210,20000211,20000212,20000213,20000214,20000215,20000218]}]}