{"Id":1085031,"Name":"Luxury Cotton Fabric","Name$english":"Luxury Cotton Fabric","Icon":"item_icons_lifematerial_cotton_cloth04","Icon2":"","Type":109,"GroupId":0,"Quality":2,"SortID":109,"Description":"A flax-spun material utilized in woven fabrications,","Description$english":"A flax-spun material utilized in woven fabrications,","Description2":1021582418,"Description2$english":"Smooth and comfortable fabric.","SexLimit":0,"Overlap":9999,"TimeType":0,"TimeLimit":"","DropModel":0,"CorrelationId":0,"SpecialDisplayType":0,"SpecialTips":0,"QuickUse":0,"IsNotice":false,"GetTips":0,"Warehouse":[101,1],"Discard":0,"LuckyTag":0,"recipes":[],"usedIn":[],"sellable":false,"sellData":null}