{"Id":1092069,"Name":"Luxury Animal Hides","Icon":"item_icons_lifematerial_fell03","Icon2":"","Type":109,"GroupId":0,"Quality":2,"SortID":109,"Description":"A field-harvested resource that can be reprocessed by life professions.","Description2":"Animal hide characterized by its aesthetically pleasing appearance and resilience.","SexLimit":0,"Overlap":9999,"TimeType":0,"TimeLimit":"","DropModel":0,"CorrelationId":0,"SpecialDisplayType":0,"SpecialTips":0,"QuickUse":0,"IsNotice":false,"GetTips":0,"Warehouse":[101,1],"Discard":1,"LuckyTag":0,"sellable":false,"sellData":null,"usedIn":[{"Id":1083054,"Name":"Residue-Free Adhesive","Type":109,"Icon":"item_icons_lifematerial_glue03","Quality":3,"amount":2},{"Id":1085034,"Name":"Premier Soft Leather","Type":109,"Icon":"item_icons_lifematerial_soft_leather04","Quality":2,"amount":2},{"Id":1085035,"Name":"Premier Hard Leather","Type":109,"Icon":"item_icons_lifematerial_hard_leather04","Quality":2,"amount":4}],"sources":[{"Name":"Fresh Meat Store","Icon":"ui/atlas/item/c_tab_icon/com_icon_tab_245","Level":0,"RoleLevel":0},{"Name":"Monster Hunt","Icon":"ui/atlas/item/c_tab_icon/com_icon_tab_90","Level":0,"RoleLevel":3},{"Name":"Monster Hunt","Icon":"ui/atlas/item/c_tab_icon/com_icon_tab_90","Level":0,"RoleLevel":3},{"Name":"Monster Hunt - Elite","Icon":"ui/atlas/item/c_tab_icon/com_icon_tab_147","Level":0,"RoleLevel":3},{"Name":"Other","Icon":"ui/atlas/item/c_tab_icon/com_icon_tab_306","Level":0,"RoleLevel":0}]}