{"Id":11010311,"Name":"Light Shutters - Large","Icon":"home_interior_decoration_curtain002_a","Icon2":"","Type":1101,"GroupId":0,"Quality":4,"SortID":11010311,"Description":"Crafted from exquisite metal, this design offers flexible light control while adding refined texture to the space.","Description2":0,"Description2$english":null,"SexLimit":0,"Overlap":9999,"TimeType":0,"TimeLimit":"","DropModel":0,"CorrelationId":0,"SpecialDisplayType":0,"SpecialTips":0,"QuickUse":0,"IsNotice":false,"GetTips":0,"Warehouse":[],"Discard":0,"LuckyTag":0,"recipes":[{"Id":2060323,"LifeProId":206,"ParentId":0,"Type":4,"Name":"Light Shutters - Large","Quality":4,"FurnitureId":11010311,"Sort":323,"Des":"Crafted from exquisite metal, this design offers flexible light control while adding refined texture to the space.","NeedLevel":50,"IsConditonUnlock":true,"UnlockType":1,"UnlockCondition":[[58,206,50]],"Cost":[20003,0],"Time":5,"NeedMaterialType":1,"NeedMaterial":[],"RandomWeight":0,"Award":[],"SpecialAward":[],"ExtraAward":[],"MasteryAward":[],"BindOrNot":1,"Exp":[],"QuickJumpType":1,"QuickJump":[8,5,505189],"Icon":"","RelatedItemId":11010311,"Hide":false}],"usedIn":[]}