{"Id":11010283,"Name":"Spirit-Leaf Plant","Icon":"home_interior_props_plant011_a","Icon2":"","Type":1101,"GroupId":0,"Quality":3,"SortID":11010283,"Description":"As an ornamental Plant, it deserves a carefully chosen vessel.","SexLimit":0,"Overlap":9999,"TimeType":0,"TimeLimit":"","DropModel":0,"CorrelationId":0,"SpecialDisplayType":0,"SpecialTips":0,"QuickUse":0,"IsNotice":false,"GetTips":0,"Warehouse":[],"Discard":0,"LuckyTag":0,"sellable":false,"sellData":null,"usedIn":[],"sources":[{"Name":"Furniture Crafting","Icon":"ui/atlas/mainui/main_btn_home","Level":0,"RoleLevel":0,"lifeSkillSource":{"Id":2020333,"LifeProId":202,"ParentId":0,"Type":4,"Name":"Spirit-Leaf Plant","Quality":3,"FurnitureId":11010283,"Sort":333,"Des":"As an ornamental Plant, it deserves a carefully chosen vessel.","NeedLevel":26,"IsConditonUnlock":true,"UnlockType":1,"UnlockCondition":["Alchemy Lv.26 to unlock"],"Cost":{"Id":20003,"Name":"Focus","Type":4,"Icon":"item_icons_energy","Quality":3,"amount":0},"Time":5,"NeedMaterialType":1,"NeedMaterial":[],"RandomWeight":0,"Award":[],"SpecialAward":[],"ExtraAward":[],"MasteryAward":[],"BindOrNot":1,"Exp":{},"QuickJumpType":1,"QuickJump":[8,5,503663],"Icon":"home_interior_props_plant011_a","RelatedItemId":11010283,"Hide":false,"awardGroups":[],"talent_lv0_yields":[],"talent_lv1_yields":[],"talent_lv2_yields":[],"talent_lv3_yields":[],"HousingExp":8,"BuildTime":28800,"materials":[{"Id":1083051,"Name":"Evergreen Agent T-3","Type":109,"Icon":"item_icons_lifematerial_plant_evergreen_reagent03","Quality":2,"amount":2},{"Id":1092053,"Name":"Base Soil","Type":109,"Icon":"item_icons_lifematerial_humus01","Quality":0,"amount":2},{"Id":1092059,"Name":"Seedlings","Type":109,"Icon":"item_icons_lifematerial_seedling01","Quality":2,"amount":1},{"Id":10010,"Name":"Homestead Coins","Type":1,"Icon":"item_icons_curreny10","Quality":2,"amount":100}]}}]}