{"Id":11010068,"Name":"Blue Square Rug","Icon":"home_interior_props_carpet006_a","Icon2":"","Type":1101,"GroupId":0,"Quality":2,"SortID":11010068,"Description":"Deep blue foundation with distinctive decorative patterns that appear to serve as a gateway to magical realms.","Description2":0,"Description2$english":null,"SexLimit":0,"Overlap":9999,"TimeType":0,"TimeLimit":"","DropModel":0,"CorrelationId":0,"SpecialDisplayType":0,"SpecialTips":0,"QuickUse":0,"IsNotice":false,"GetTips":0,"Warehouse":[],"Discard":0,"LuckyTag":0,"recipes":[{"Id":2060308,"LifeProId":206,"ParentId":0,"Type":4,"Name":"Blue Square Rug","Quality":2,"FurnitureId":11010068,"Sort":308,"Des":"Deep blue foundation with distinctive decorative patterns that appear to serve as a gateway to magical realms.","NeedLevel":10,"IsConditonUnlock":true,"UnlockType":1,"UnlockCondition":[[58,206,10]],"Cost":[20003,0],"Time":5,"NeedMaterialType":1,"NeedMaterial":[],"RandomWeight":0,"Award":[],"SpecialAward":[],"ExtraAward":[],"MasteryAward":[],"BindOrNot":1,"Exp":[],"QuickJumpType":1,"QuickJump":[8,5,505189],"Icon":"","RelatedItemId":11010068,"Hide":false}],"usedIn":[]}