{"Id":2010323,"Name":"Wane Feltcap","Icon":"headwear_icon_c_armormagic01","Icon2":"","Type":201,"GroupId":0,"Quality":3,"SortID":2013002,"Description":"Seems to gain higher Intellect attributes.<br><br>[This gear's advanced attributes will not include Crit]","Description2":"A classic outfit set designed specifically for reconnaissance, made from comfortable and durable materials, easy to move in and beloved by adventurers.","SexLimit":0,"Overlap":1,"TimeType":0,"TimeLimit":"","DropModel":0,"CorrelationId":0,"SpecialDisplayType":0,"SpecialTips":0,"QuickUse":0,"IsNotice":false,"GetTips":0,"Warehouse":[],"Discard":0,"LuckyTag":0,"sellable":false,"sellData":null,"usedIn":[],"sources":[{"Name":"Monster Hunt - Boss","Icon":"ui/atlas/item/c_tab_icon/com_icon_tab_146","Level":0,"RoleLevel":3}]}