{"Id":2070319,"Name":"Lucky Emerald Ring","Name$english":"Lucky Emerald Ring","Icon":"ring_icon_m_fangxing02","Icon2":"","Type":207,"GroupId":0,"Quality":4,"SortID":2073004,"Description":"Seems to provide higher agility attributes.","Description$english":"Seems to provide higher agility attributes.","Description2":164204342,"Description2$english":"Bahamar Gem Ring, with a gentle luster and exquisite Artisanship, is highly sought after by adventurers.","SexLimit":0,"Overlap":1,"TimeType":0,"TimeLimit":"","DropModel":0,"CorrelationId":0,"SpecialDisplayType":0,"SpecialTips":0,"QuickUse":0,"IsNotice":false,"GetTips":0,"Warehouse":[],"Discard":0,"LuckyTag":0,"recipes":[],"usedIn":[],"sellable":false}