{"Id":3010004,"Name":"Will - Shadow Captain","Icon":"skill_aoyi_draw_icon_010","Icon2":"","Type":301,"GroupId":0,"Quality":3,"SortID":1055004,"Description":"Imprinted with the battle consciousness of Shadow Captain, can be used to create Battle Imagine - Shadow Captain.","Description2":"Battle Imagine is the crystallization of thoughts, consciousness, and Engram combined, possessing supernatural powers.","SexLimit":0,"Overlap":9999,"TimeType":0,"TimeLimit":"","DropModel":0,"CorrelationId":0,"SpecialDisplayType":0,"SpecialTips":0,"QuickUse":0,"IsNotice":false,"GetTips":0,"Warehouse":[],"Discard":0,"LuckyTag":0,"sellable":true,"sellData":{"ItemID":3010004,"Index":44,"Category":1,"Subcategory":103,"OnceSaleLimit":9999,"OnceLimit":9999,"RecommendedPrice":150000,"MinPercentage":20,"MaxPercentage":50,"EachPercentage":5,"Minimum":37500,"Maximum":750000,"BottomBuyLimit":1,"CalmTradePeriod":30,"TaxPercentage":5,"MonthCardTaxPercentage":4,"DepositPercentage":1,"MonthCardDepositPercentage":0,"DelayedTime":[1200,5400],"ListingTime":86400,"Currency":10002,"Publicity":0,"PublicityTime":0,"OrderLimt":0,"PriceWatch":0,"FitterId":[],"AutoSale":0,"AutoSaleTimeLimit":0,"AutoSaleNumLimit":[],"AutoSaleTime":[],"AutoSaleTimeRate":[],"AutoSaleLimit":0,"AutoSaleRate":0,"AutoSaleNum":[],"AutoSalePriceRange":[],"OnceAutoNumLimit":0,"RecycleQueue":0,"RecycleRank":0,"RecycleLimit":0,"RecycleNunLimit":[],"AdaptChange":[],"HideItem":false},"usedIn":[],"sources":[{"Name":"Miracle Star Chest","Icon":"ui/atlas/item/c_tab_icon/com_icon_tab_139","Level":0,"RoleLevel":0},{"Name":"Battle Will Exchange","Icon":"ui/atlas/item/c_tab_icon/com_icon_tab_83","Level":0,"RoleLevel":0},{"Name":"Stimen Vaults","Icon":"ui/atlas/item/c_tab_icon/com_icon_tab_126","Level":0,"RoleLevel":20},{"Name":"Monster Hunt - Elite","Icon":"ui/atlas/item/c_tab_icon/com_icon_tab_147","Level":0,"RoleLevel":3},{"Name":"Will Wish","Icon":"ui/atlas/item/c_tab_icon/com_icon_tab_171","Level":0,"RoleLevel":2},{"Name":"Dismantle","Icon":"ui/atlas/item/c_tab_icon/com_icon_tab_198","Level":0,"RoleLevel":0},{"Name":"Trading Center","Icon":"ui/atlas/item/c_tab_icon/com_icon_tab_181","Level":0,"RoleLevel":9,"tradingInfo":{"ItemID":3010004,"Index":44,"Category":1,"Subcategory":103,"OnceSaleLimit":9999,"OnceLimit":9999,"RecommendedPrice":150000,"MinPercentage":20,"MaxPercentage":50,"EachPercentage":5,"Minimum":37500,"Maximum":750000,"BottomBuyLimit":1,"CalmTradePeriod":30,"TaxPercentage":5,"MonthCardTaxPercentage":4,"DepositPercentage":1,"MonthCardDepositPercentage":0,"DelayedTime":[1200,5400],"ListingTime":86400,"Currency":10002,"Publicity":0,"PublicityTime":0,"OrderLimt":0,"PriceWatch":0,"FitterId":[],"AutoSale":0,"AutoSaleTimeLimit":0,"AutoSaleNumLimit":[],"AutoSaleTime":[],"AutoSaleTimeRate":[],"AutoSaleLimit":0,"AutoSaleRate":0,"AutoSaleNum":[],"AutoSalePriceRange":[],"OnceAutoNumLimit":0,"RecycleQueue":0,"RecycleRank":0,"RecycleLimit":0,"RecycleNunLimit":[],"AdaptChange":[],"HideItem":false}}]}