{"Id":40008,"Name":"Oct 2025 Collection Card (currently unused, reserved for Monthly Card compensation)","Name$english":"Oct 2025 Collection Card (currently unused, reserved for Monthly Card compensation)","Icon":"item_icons_monthcard001","Icon2":"","Type":103,"GroupId":0,"Quality":4,"SortID":101,"Description":"Oct 2025 Collection Card (currently unused, reserved for Monthly Card compensation)","Description$english":"Oct 2025 Collection Card (currently unused, reserved for Monthly Card compensation)","Description2":509313260,"Description2$english":"Oct 2025 Collection Card (currently unused, reserved for Monthly Card compensation)","SexLimit":0,"Overlap":1,"TimeType":0,"TimeLimit":"","DropModel":0,"CorrelationId":0,"SpecialDisplayType":0,"SpecialTips":0,"QuickUse":0,"IsNotice":false,"GetTips":0,"Warehouse":[],"Discard":0,"LuckyTag":0,"recipes":[],"usedIn":[],"sellable":false}