{"Id":7037050,"Name":"Dream Cruise - Bottom","Icon":"pants_icon_f_sailor01","Icon2":"","Type":703,"GroupId":0,"Quality":3,"SortID":7037050,"Description":"If you own these outfits, you can go to the wardrobe to dress up and become the most dazzling adventurer!","Description2":174597974,"Description2$english":"Asterleeds is a city of fashion, where designers create beautiful designs in clothing, accessories, and jewelry of various styles. People are passionate about collecting these fashion items and matching them according to their preferences.","SexLimit":2,"Overlap":-1,"TimeType":0,"TimeLimit":"","DropModel":0,"CorrelationId":7037050,"SpecialDisplayType":0,"SpecialTips":1,"QuickUse":0,"IsNotice":false,"GetTips":0,"Warehouse":[],"Discard":0,"LuckyTag":0,"recipes":[],"usedIn":[]}