[{"node":"0a","edge":null,"parent":null,"Id":11010261,"Name":"Gunny Sack","Type":1101,"Icon":"home_interior_props_bag001_a","Quality":2,"recipe":{"Id":2060301,"RelatedItemId":11010261,"Name":"Gunny Sack","Cost":{"Id":20003,"Name":"Stamina","Type":4,"Icon":"item_icons_energy","Quality":3,"amount":0},"Time":5,"NeedMaterial":[],"NeedMaterialType":1,"UnlockCondition":["Weaving Lv.3 to unlock"],"LifeProId":206,"Exp":{},"SpecialAward":[],"talent_lv0_yields":[],"talent_lv1_yields":[],"talent_lv2_yields":[],"talent_lv3_yields":[]}},{"node":"1a","edge":"0a-1a","parent":"0a","Id":1085013,"Name":"Refined Canvas","Type":109,"Icon":"item_icons_lifematerial_canvas01","Quality":1,"amount":3,"recipe":{"Id":2060203,"RelatedItemId":1085013,"Name":"Refined Canvas","Cost":{"Id":20003,"Name":"Stamina","Type":4,"Icon":"item_icons_energy","Quality":3,"amount":0},"Time":5,"NeedMaterial":[[1085011,3],[1083039,1]],"NeedMaterialType":1,"UnlockCondition":["Weaving Lv.1 to unlock"],"LifeProId":206,"Exp":{"Id":31091,"Name":"Weaving EXP","Type":31,"Icon":"item_icons_process_exp_01","Quality":1,"amount":2},"SpecialAward":[],"talent_lv0_yields":[[{"itemId":1085013,"Name":"Refined Canvas","rate":1,"Icon":"item_icons_lifematerial_canvas01","Quality":1,"amount":1}]],"talent_lv1_yields":[[{"itemId":1085013,"Name":"Refined Canvas","rate":1,"Icon":"item_icons_lifematerial_canvas01","Quality":1,"amount":1}]],"talent_lv2_yields":[[{"itemId":1085013,"Name":"Refined Canvas","rate":1,"Icon":"item_icons_lifematerial_canvas01","Quality":1,"amount":1}]],"talent_lv3_yields":[[{"itemId":1085013,"Name":"Refined Canvas","rate":1,"Icon":"item_icons_lifematerial_canvas01","Quality":1,"amount":1}]]}},{"node":"1b","edge":"0a-1b","parent":"0a","Id":1085011,"Name":"Refined Yarn","Type":109,"Icon":"item_icons_lifematerial_thread01","Quality":1,"amount":3,"recipe":{"Id":2060201,"RelatedItemId":1085011,"Name":"Refined Yarn ×3","Cost":{"Id":20003,"Name":"Stamina","Type":4,"Icon":"item_icons_energy","Quality":3,"amount":0},"Time":5,"NeedMaterial":[[1092033,1]],"NeedMaterialType":1,"UnlockCondition":["Weaving Lv.1 to unlock"],"LifeProId":206,"Exp":{"Id":31091,"Name":"Weaving EXP","Type":31,"Icon":"item_icons_process_exp_01","Quality":1,"amount":2},"SpecialAward":[],"talent_lv0_yields":[[{"itemId":1085011,"Name":"Refined Yarn","rate":1,"Icon":"item_icons_lifematerial_thread01","Quality":1,"amount":3}]],"talent_lv1_yields":[[{"itemId":1085011,"Name":"Refined Yarn","rate":1,"Icon":"item_icons_lifematerial_thread01","Quality":1,"amount":3}]],"talent_lv2_yields":[[{"itemId":1085011,"Name":"Refined Yarn","rate":1,"Icon":"item_icons_lifematerial_thread01","Quality":1,"amount":3}]],"talent_lv3_yields":[[{"itemId":1085011,"Name":"Refined Yarn","rate":1,"Icon":"item_icons_lifematerial_thread01","Quality":1,"amount":3}]]}},{"node":"1c","edge":"0a-1c","parent":"0a","Id":10010,"Name":"Homestead Coins","Type":1,"Icon":"item_icons_curreny10","Quality":2,"amount":50,"recipe":null},{"node":"2a","edge":"1a-2a","parent":"1a","Id":1085011,"Name":"Refined Yarn","Type":109,"Icon":"item_icons_lifematerial_thread01","Quality":1,"amount":3,"recipe":{"Id":2060201,"RelatedItemId":1085011,"Name":"Refined Yarn ×3","Cost":{"Id":20003,"Name":"Stamina","Type":4,"Icon":"item_icons_energy","Quality":3,"amount":0},"Time":5,"NeedMaterial":[[1092033,1]],"NeedMaterialType":1,"UnlockCondition":["Weaving Lv.1 to unlock"],"LifeProId":206,"Exp":{"Id":31091,"Name":"Weaving EXP","Type":31,"Icon":"item_icons_process_exp_01","Quality":1,"amount":2},"SpecialAward":[],"talent_lv0_yields":[[{"itemId":1085011,"Name":"Refined Yarn","rate":1,"Icon":"item_icons_lifematerial_thread01","Quality":1,"amount":3}]],"talent_lv1_yields":[[{"itemId":1085011,"Name":"Refined Yarn","rate":1,"Icon":"item_icons_lifematerial_thread01","Quality":1,"amount":3}]],"talent_lv2_yields":[[{"itemId":1085011,"Name":"Refined Yarn","rate":1,"Icon":"item_icons_lifematerial_thread01","Quality":1,"amount":3}]],"talent_lv3_yields":[[{"itemId":1085011,"Name":"Refined Yarn","rate":1,"Icon":"item_icons_lifematerial_thread01","Quality":1,"amount":3}]]}},{"node":"2b","edge":"1a-2b","parent":"1a","Id":1083039,"Name":"Beeswax","Type":109,"Icon":"item_icons_lifematerial_wax01","Quality":1,"amount":1,"recipe":{"Id":2020209,"RelatedItemId":1083039,"Name":"Beeswax","Cost":{"Id":20003,"Name":"Stamina","Type":4,"Icon":"item_icons_energy","Quality":3,"amount":0},"Time":5,"NeedMaterial":[[1092073,3]],"NeedMaterialType":1,"UnlockCondition":["Alchemy Lv.1 to unlock"],"LifeProId":202,"Exp":{"Id":31051,"Name":"Alchemy EXP","Type":31,"Icon":"item_icons_alchemy_exp_01","Quality":1,"amount":2},"SpecialAward":[],"talent_lv0_yields":[[{"itemId":1083039,"Name":"Beeswax","rate":1,"Icon":"item_icons_lifematerial_wax01","Quality":1,"amount":1}]],"talent_lv1_yields":[[{"itemId":1083039,"Name":"Beeswax","rate":1,"Icon":"item_icons_lifematerial_wax01","Quality":1,"amount":1}]],"talent_lv2_yields":[[{"itemId":1083039,"Name":"Beeswax","rate":1,"Icon":"item_icons_lifematerial_wax01","Quality":1,"amount":1}]],"talent_lv3_yields":[[{"itemId":1083039,"Name":"Beeswax","rate":1,"Icon":"item_icons_lifematerial_wax01","Quality":1,"amount":1}]]}},{"node":"2c","edge":"1b-2c","parent":"1b","Id":1092033,"Name":"Flax","Type":109,"Icon":"item_icons_lifematerial_flax01","Quality":2,"amount":1,"recipe":null,"lifeSkillSources":[{"Id":20000007,"Name":"​Grey-top Flax","Cost":{"Id":20003,"Name":"Stamina","Type":4,"Icon":"item_icons_energy","Quality":3,"amount":0},"UnlockCondition":[],"UnlockConditionZeroCost":["Botany Lv.1 to unlock"],"LifeProId":101,"isFree":true}]},{"node":"3a","edge":"2a-3a","parent":"2a","Id":1092033,"Name":"Flax","Type":109,"Icon":"item_icons_lifematerial_flax01","Quality":2,"amount":1,"recipe":null,"lifeSkillSources":[{"Id":20000007,"Name":"​Grey-top Flax","Cost":{"Id":20003,"Name":"Stamina","Type":4,"Icon":"item_icons_energy","Quality":3,"amount":0},"UnlockCondition":[],"UnlockConditionZeroCost":["Botany Lv.1 to unlock"],"LifeProId":101,"isFree":true}]},{"node":"3b","edge":"2b-3b","parent":"2b","Id":1092073,"Name":"Beehive","Type":109,"Icon":"item_icons_lifematerial_beehive01","Quality":0,"amount":3,"recipe":null}]